aiohttp_s3_client/__init__.py
aiohttp_s3_client/client.py
aiohttp_s3_client/credentials.py
aiohttp_s3_client/py.typed
aiohttp_s3_client/version.py
aiohttp_s3_client/xml.py
aiohttp_s3_client-1.0.14.dist-info/METADATA
aiohttp_s3_client-1.0.14.dist-info/WHEEL
aiohttp_s3_client-1.0.14.dist-info/licenses/LICENSE
aiohttp_s3_client-1.0.14.dist-info/licenses/LICENSE.md
aiohttp_s3_client-1.0.14.dist-info/RECORD
