Metadata-Version: 2.4
Name: aiohttp-s3-client
Version: 1.0.14
Summary: The simple module for putting and getting object from Amazon S3 compatible endpoints
License: Apache Software License
License-File: LICENSE
License-File: LICENSE.md
Author: Dmitry Orlov
Author-email: me@mosquito.su
Requires-Python: >=3.10,<4.0
Classifier: Development Status :: 4 - Beta
Classifier: Intended Audience :: Developers
Classifier: License :: OSI Approved :: Apache Software License
Classifier: License :: Other/Proprietary License
Classifier: Natural Language :: English
Classifier: Operating System :: MacOS
Classifier: Operating System :: Microsoft
Classifier: Operating System :: POSIX
Classifier: Programming Language :: Python
Classifier: Programming Language :: Python :: 3
Classifier: Programming Language :: Python :: 3.10
Classifier: Programming Language :: Python :: 3.11
Classifier: Programming Language :: Python :: 3.12
Classifier: Programming Language :: Python :: 3.13
Classifier: Programming Language :: Python :: 3.14
Classifier: Programming Language :: Python :: 3.8
Classifier: Programming Language :: Python :: 3.9
Classifier: Programming Language :: Python :: Implementation :: CPython
Classifier: Programming Language :: Python :: Implementation :: PyPy
Classifier: Topic :: Internet
Classifier: Topic :: Software Development
Classifier: Topic :: Software Development :: Libraries
Requires-Dist: aiohttp (>=3.8,<4.0)
Requires-Dist: aiomisc (>=17.3.4,<18.0.0)
Requires-Dist: aws-request-signer (==1.2.0)
Requires-Dist: typing_extensions ; python_version < "3.10"
Project-URL: Homepage, https://github.com/aiokitchen/aiohttp-s3-client
Project-URL: Source, https://github.com/aiokitchen/aiohttp-s3-client
Project-URL: Tracker, https://github.com/aiokitchen/aiohttp-s3-client/issues
